dbTelematelAPI/__init__.py
dbTelematelAPI/__main__.py
dbTelematelAPI/query_pasarela.py
dbTelematelAPI/telematel_wrapper.py
dbTelematelAPI-0.0.8.dist-info/METADATA
dbTelematelAPI-0.0.8.dist-info/WHEEL
dbTelematelAPI-0.0.8.dist-info/license.txt
dbTelematelAPI-0.0.8.dist-info/top_level.txt
dbTelematelAPI-0.0.8.dist-info/RECORD
