Metadata-Version: 2.2
Name: dbTelematelAPI
Version: 0.0.8
Summary: Permite consumir el API de Telematel
Home-page: https://github.com/jmsanchez-ibiza/dbTelematelAPI
Author: José María Sánchez González
Author-email: miotroyo1970@gmail.com
License: MIT
Keywords: jmsanchez-ibiza
Classifier: Development Status :: 3 - Alpha
Classifier: Intended Audience :: Developers
Classifier: Topic :: Software Development :: Build Tools
Classifier: License :: OSI Approved :: MIT License
Classifier: Programming Language :: Python :: 3
License-File: license.txt
Requires-Dist: requests
Requires-Dist: pyodbc
Dynamic: author
Dynamic: author-email
Dynamic: classifier
Dynamic: description
Dynamic: description-content-type
Dynamic: home-page
Dynamic: keywords
Dynamic: license
Dynamic: requires-dist
Dynamic: summary
